bavard/__init__.py
bavard/__main__.py
bavard/config.py
bavard/common/__init__.py
bavard/common/model_base.py
bavard/common/pretrained_bases.py
bavard/common/serialization.py
bavard/common/layers/__init__.py
bavard/common/layers/attention_pooling.py
bavard/common/layers/dense.py
bavard/common/layers/lstm.py
bavard/common/layers/text_embedder.py
bavard/common/layers/transformer.py
bavard/dialogue_policy/__init__.py
bavard/dialogue_policy/cli.py
bavard/dialogue_policy/constants.py
bavard/dialogue_policy/data/__init__.py
bavard/dialogue_policy/data/preprocessed_data.py
bavard/dialogue_policy/data/utils.py
bavard/dialogue_policy/data/encode/__init__.py
bavard/dialogue_policy/data/encode/actions.py
bavard/dialogue_policy/data/encode/conversation.py
bavard/dialogue_policy/data/encode/dialogue_turns.py
bavard/dialogue_policy/models/__init__.py
bavard/dialogue_policy/models/base.py
bavard/dialogue_policy/models/classifier.py
bavard/dialogue_policy/models/utils.py
bavard/dialogue_policy/models/unidirectional_transformer/__init__.py
bavard/dialogue_policy/models/unidirectional_transformer/attention.py
bavard/dialogue_policy/models/unidirectional_transformer/encoder.py
bavard/dialogue_policy/models/unidirectional_transformer/encoder_layer.py
bavard/dialogue_policy/models/unidirectional_transformer/ffn.py
bavard/dialogue_policy/models/unidirectional_transformer/masking.py
bavard/dialogue_policy/models/unidirectional_transformer/pos_enc.py
bavard/dialogue_policy/models/unidirectional_transformer/transformer.py
bavard/dialogue_policy/scripts/__init__.py
bavard/dialogue_policy/scripts/mwoz2_2_extract_hotel_conversations.py
bavard/mlops/__init__.py
bavard/mlops/deploy.py
bavard/mlops/gcs.py
bavard/mlops/pipeline.py
bavard/mlops/pydantics.py
bavard/mlops/train.py
bavard/nlu/__init__.py
bavard/nlu/auto_setup.py
bavard/nlu/cli.py
bavard/nlu/constants.py
bavard/nlu/metrics.py
bavard/nlu/model.py
bavard/nlu/pydantics.py
bavard/nlu/utils.py
bavard/nlu/vwci.py
bavard/nlu/data/__init__.py
bavard-0.0.57.dist-info/METADATA
bavard-0.0.57.dist-info/WHEEL
bavard-0.0.57.dist-info/entry_points.txt
bavard-0.0.57.dist-info/top_level.txt
bavard-0.0.57.dist-info/RECORD
