Metadata-Version: 2.1
Name: bavard
Version: 0.0.57
Summary: A library and CLI for NLP and chatbot tasks
Home-page: https://github.com/bavard-ai/bavard-nlu
Author: Bavard AI, Inc.
Author-email: dev@bavard.ai
License: UNKNOWN
Platform: UNKNOWN
Classifier: Programming Language :: Python :: 3
Classifier: License :: OSI Approved :: MIT License
Classifier: Operating System :: OS Independent
Requires-Python: >=3.6
Requires-Dist: bavard-ml-common (==0.1.15)
Requires-Dist: fire (==0.4.0)
Requires-Dist: keras-tuner (==1.0.2)
Requires-Dist: loguru (==0.5.3)
Requires-Dist: numpy (==1.18.5)
Requires-Dist: pydantic (==1.7.3)
Requires-Dist: scikit-learn (==0.24.1)
Requires-Dist: sentencepiece (==0.1.95)
Requires-Dist: spacy (==3.0.1)
Requires-Dist: tensorflow-probability (==0.11.1)
Requires-Dist: tensorflow (==2.3.2)
Requires-Dist: transformers (==4.3.0)
Requires-Dist: uncertainty-metrics (==0.0.81)
Requires-Dist: uvicorn (==0.13.3)
